<DOMSymbolItem xmlns:xsi="http://www.w3.org/2001/XMLSchema-instance" xmlns="http://ns.adobe.com/xfl/2008/" name="PeasantGraphic" itemID="50ccf467-0000026f" symbolType="graphic" lastModified="1355629706">
  <timeline>
    <DOMTimeline name="PeasantGraphic">
      <layers>
        <DOMLayer name="Layer 18" color="#9933CC">
          <frames>
            <DOMFrame index="0" duration="14" keyMode="9728">
              <elements>
                <DOMShape>
                  <fills>
                    <FillStyle index="1">
                      <SolidColor color="#F4B678"/>
                    </FillStyle>
                  </fills>
                  <strokes>
                    <StrokeStyle index="1">
                      <SolidStroke scaleMode="normal">
                        <fill>
                          <SolidColor color="#654806"/>
                        </fill>
                      </SolidStroke>
                    </StrokeStyle>
                  </strokes>
                  <edges>
                    <Edge fillStyle1="1" strokeStyle="1" edges="!377 630[347 601 347 560!347 560[347 519 377 489!377 489[409 461 429 471!429 471[448 481 426 534!426 534[401 584 517 625!517 625[632 665 601 695!601 695[569 722 490 691!490 691[409 659 377 630"/>
                  </edges>
                </DOMShape>
              </elements>
            </DOMFrame>
          </frames>
        </DOMLayer>
        <DOMLayer name="Layer 17" color="#4FFF4F">
          <frames>
            <DOMFrame index="0" duration="14" keyMode="9728">
              <elements>
                <DOMShape>
                  <fills>
                    <FillStyle index="1">
                      <SolidColor color="#F4B678"/>
                    </FillStyle>
                  </fills>
                  <strokes>
                    <StrokeStyle index="1">
                      <SolidStroke scaleMode="normal">
                        <fill>
                          <SolidColor color="#654806"/>
                        </fill>
                      </SolidStroke>
                    </StrokeStyle>
                  </strokes>
                  <edges>
                    <Edge fillStyle1="1" strokeStyle="1" edges="!552 312[552 307 557 302!557 302[562 298 568 298!568 298[574 298 578 302!578 302[582 307 582 312!582 312[582 318 578 323!578 323[574 326 568 326!568 326[562 326 557 323!557 323[552 318 552 312!622 307[632 298 644 298!644 298[655 298 665
 307!665 307[674 314 674 326!674 326[674 338 665 346!665 346[655 355 644 355!644 355[632 355 622 346!622 346[613 338 613 326!613 326[613 314 622 307"/>
                  </edges>
                </DOMShape>
              </elements>
            </DOMFrame>
          </frames>
        </DOMLayer>
        <DOMLayer name="Layer 15" color="#4F80FF">
          <frames>
            <DOMFrame index="0" duration="14" keyMode="9728">
              <elements>
                <DOMShape>
                  <fills>
                    <FillStyle index="1">
                      <SolidColor color="#F4B678"/>
                    </FillStyle>
                  </fills>
                  <strokes>
                    <StrokeStyle index="1">
                      <SolidStroke scaleMode="normal">
                        <fill>
                          <SolidColor color="#654806"/>
                        </fill>
                      </SolidStroke>
                    </StrokeStyle>
                  </strokes>
                  <edges>
                    <Edge fillStyle1="1" strokeStyle="1" edges="
!504 248[536 225 566 233!566 233[596 241 608 275!608 275[622 307 612 346!612 346[600 386 570 409!570 409[542 431 511 424!511 424[480 415 465 385!465 385[453 349 465 310!465 310[477 270 504 248"/>
                  </edges>
                </DOMShape>
              </elements>
            </DOMFrame>
          </frames>
        </DOMLayer>
        <DOMLayer name="Layer 16" color="#FF4F4F">
          <frames>
            <DOMFrame index="0" duration="14" keyMode="9728">
              <elements>
                <DOMShape>
                  <fills>
                    <FillStyle index="1">
                      <SolidColor color="#F4B678"/>
                    </FillStyle>
                  </fills>
                  <strokes>
                    <StrokeStyle index="1">
                      <SolidStroke scaleMode="normal">
                        <fill>
                          <SolidColor color="#654806"/>
                        </fill>
                      </SolidStroke>
                    </StrokeStyle>
                  </strokes>
                  <edges>
                    <Edge fillStyle1="1" strokeStyle="1" edges="
!658 245[699 234 733 247!733 247[771 260 779 289!779 289[787 317 762 343!762 343[739 371 697 382!697 382[653 392 618 382!618 382[582 367 574 342!574 342[566 312 587 284!587 284[614 257 658 245"/>
                  </edges>
                </DOMShape>
              </elements>
            </DOMFrame>
          </frames>
        </DOMLayer>
        <DOMLayer name="Layer 14" color="#808080">
          <frames>
            <DOMFrame index="0" duration="14" keyMode="9728">
              <elements>
                <DOMShape>
                  <fills>
                    <FillStyle index="1">
                      <SolidColor color="#F4B678"/>
                    </FillStyle>
                  </fills>
                  <strokes>
                    <StrokeStyle index="1">
                      <SolidStroke scaleMode="normal">
                        <fill>
                          <SolidColor color="#654806"/>
                        </fill>
                      </SolidStroke>
                    </StrokeStyle>
                  </strokes>
                  <edges>
                    <Edge fillStyle1="1" strokeStyle="1" edges="
!127 383[170 383 201 403!201 403[233 424 233 455!233 455[233 483 201 504!201 504[170 524 127 524!127 524[82 524 50 504!50 504[20 483 20 455!20 455[20 424 50 403!50 403[82 383 127 383"/>
                  </edges>
                </DOMShape>
              </elements>
            </DOMFrame>
          </frames>
        </DOMLayer>
        <DOMLayer name="Layer 13" color="#4FFFFF">
          <frames>
            <DOMFrame index="0" duration="14" keyMode="9728">
              <elements>
                <DOMShape>
                  <fills>
                    <FillStyle index="1">
                      <SolidColor color="#F4B678"/>
                    </FillStyle>
                  </fills>
                  <strokes>
                    <StrokeStyle index="1">
                      <SolidStroke scaleMode="normal">
                        <fill>
                          <SolidColor color="#654806"/>
                        </fill>
                      </SolidStroke>
                    </StrokeStyle>
                  </strokes>
                  <edges>
                    <Edge fillStyle1="1" strokeStyle="1" edges="
!541 417[564 385 573 380!573 380[581 374 733 401!733 401[884 425 951 489!951 489[1016 552 990 612!990 612[964 673 879 691!879 691[796 710 711 659!711 659[638 617 580 566"/>
                    <Edge fillStyle1="1" edges="
!580 566[568 556 557 545!557 545[490 481 526 434!526 434[532 424 541 417"/>
                  </edges>
                </DOMShape>
              </elements>
            </DOMFrame>
          </frames>
        </DOMLayer>
        <DOMLayer name="Layer 12" color="#FF4FFF">
          <frames>
            <DOMFrame index="0" duration="14" keyMode="9728">
              <elements>
                <DOMShape>
                  <fills>
                    <FillStyle index="1">
                      <SolidColor color="#F4B678"/>
                    </FillStyle>
                  </fills>
                  <strokes>
                    <StrokeStyle index="1">
                      <SolidStroke scaleMode="normal">
                        <fill>
                          <SolidColor color="#654806"/>
                        </fill>
                      </SolidStroke>
                    </StrokeStyle>
                  </strokes>
                  <edges>
                    <Edge fillStyle1="1" strokeStyle="1" edges="
!419 60[448 88 427 120!427 120[408 149 366 156!366 156[325 160 300 189!300 189[275 218 229 194!229 194[183 169 197 126!197 126[211 83 243 53!243 53[275 25 332 29!332 29[390 31 419 60"/>
                  </edges>
                </DOMShape>
              </elements>
            </DOMFrame>
          </frames>
        </DOMLayer>
        <DOMLayer name="Layer 11" color="#FF800A">
          <frames>
            <DOMFrame index="0" duration="14" keyMode="9728">
              <elements>
                <DOMShape>
                  <fills>
                    <FillStyle index="1">
                      <SolidColor color="#F4B678"/>
                    </FillStyle>
                  </fills>
                  <strokes>
                    <StrokeStyle index="1">
                      <SolidStroke scaleMode="normal">
                        <fill>
                          <SolidColor color="#654806"/>
                        </fill>
                      </SolidStroke>
                    </StrokeStyle>
                  </strokes>
                  <edges>
                    <Edge fillStyle1="1" strokeStyle="1" edges="
!638 662/704 729!704 729/704 838!704 838[429 934 156 811!156 811[149 313 328 79!328 79[512 334 638 662"/>
                    <Edge cubics="!704 838(;521,901 337,894 156,811q704 838Q429 934q156 811);"/>
                    <Edge cubics="!704 729(;704,729 704,838 704,838q704 729 704 838);"/>
                    <Edge cubics="!638 662(;638,662 704,729 704,729q638 662 704 729);"/>
                    <Edge cubics="!156 811(;151,479 208,236 328,79q156 811Q149 313q328 79);"/>
                    <Edge cubics="!328 79(;451,249 554,444 638,662q328 79Q512 334q638 662);"/>
                  </edges>
                </DOMShape>
              </elements>
            </DOMFrame>
          </frames>
        </DOMLayer>
        <DOMLayer name="arm" color="#FF800A" autoNamed="false" layerType="folder"/>
        <DOMLayer name="Layer 3" color="#FF800A" parentLayerIndex="8">
          <frames>
            <DOMFrame index="0" duration="6" keyMode="9728">
              <elements>
                <DOMShape>
                  <fills>
                    <FillStyle index="1">
                      <SolidColor color="#F4B678"/>
                    </FillStyle>
                  </fills>
                  <strokes>
                    <StrokeStyle index="1">
                      <SolidStroke scaleMode="normal">
                        <fill>
                          <SolidColor color="#654806"/>
                        </fill>
                      </SolidStroke>
                    </StrokeStyle>
                  </strokes>
                  <edges>
                    <Edge fillStyle1="1" strokeStyle="1" edges="
!303 912[301 906 300 900!300 900[298 863 314 819!314 819[328 774 354 749!354 749[357 746 361 744!361 744[386 727 406 733!406 733[414 736 418 744!418 744[424 758 418 787!418 787[406 832 404 869!404 869[402 906 378 929!378 929[375 931 373
 933"/>
                    <Edge fillStyle1="1" edges="
!373 933|372 934!372 934[350 950 332 945!332 945[322 942 315 934!315 934[307 926 303 912"/>
                  </edges>
                </DOMShape>
              </elements>
            </DOMFrame>
            <DOMFrame index="6" duration="7" keyMode="9728">
              <elements>
                <DOMShape>
                  <fills>
                    <FillStyle index="1">
                      <SolidColor color="#F4B678"/>
                    </FillStyle>
                  </fills>
                  <strokes>
                    <StrokeStyle index="1">
                      <SolidStroke scaleMode="normal">
                        <fill>
                          <SolidColor color="#654806"/>
                        </fill>
                      </SolidStroke>
                    </StrokeStyle>
                  </strokes>
                  <edges>
                    <Edge fillStyle1="1" strokeStyle="1" edges="
!340 928[336 922 334 916!334 916[322 882 326 835!326 835[328 788 347 756!347 756[349 754 353 751!353 751[372 727 393 728!393 728[401 729 408 736!408 736[417 747 419 777!419 777[418 824 426 859!426 859[433 896 416 924!416 924[414 927 412
 929"/>
                    <Edge fillStyle1="1" edges="
!412 929|412 931!412 931[395 952 377 952!377 952[366 952 357 945!357 945[348 940 340 928"/>
                  </edges>
                </DOMShape>
              </elements>
            </DOMFrame>
            <DOMFrame index="13" keyMode="9728">
              <elements>
                <DOMShape>
                  <fills>
                    <FillStyle index="1">
                      <SolidColor color="#F4B678"/>
                    </FillStyle>
                  </fills>
                  <strokes>
                    <StrokeStyle index="1">
                      <SolidStroke scaleMode="normal">
                        <fill>
                          <SolidColor color="#654806"/>
                        </fill>
                      </SolidStroke>
                    </StrokeStyle>
                  </strokes>
                  <edges>
                    <Edge fillStyle1="1" strokeStyle="1" edges="
!303 912[301 906 300 900!300 900[298 863 314 819!314 819[328 774 354 749!354 749[357 746 361 744!361 744[386 727 406 733!406 733[414 736 418 744!418 744[424 758 418 787!418 787[406 832 404 869!404 869[402 906 378 929!378 929[375 931 373
 933"/>
                    <Edge fillStyle1="1" edges="
!373 933|372 934!372 934[350 950 332 945!332 945[322 942 315 934!315 934[307 926 303 912"/>
                  </edges>
                </DOMShape>
              </elements>
            </DOMFrame>
          </frames>
        </DOMLayer>
        <DOMLayer name="Layer 4" color="#FF4FFF" parentLayerIndex="8">
          <frames>
            <DOMFrame index="0" duration="6" keyMode="9728">
              <elements>
                <DOMShape>
                  <fills>
                    <FillStyle index="1">
                      <SolidColor color="#F4B678"/>
                    </FillStyle>
                  </fills>
                  <strokes>
                    <StrokeStyle index="1">
                      <SolidStroke scaleMode="normal">
                        <fill>
                          <SolidColor color="#654806"/>
                        </fill>
                      </SolidStroke>
                    </StrokeStyle>
                  </strokes>
                  <edges>
                    <Edge fillStyle1="1" strokeStyle="1" edges="
!377 893[388 908 369 944!369 944[347 978 330 1041!330 1041[315 1105 262 1099!262 1099[206 1093 190 1075!190 1075[171 1051 190 1015!190 1015[214 982 253 947!253 947[294 912 329 895!329 895[365 880 377 893"/>
                  </edges>
                </DOMShape>
              </elements>
            </DOMFrame>
            <DOMFrame index="6" duration="7" keyMode="9728">
              <elements>
                <DOMShape>
                  <fills>
                    <FillStyle index="1">
                      <SolidColor color="#F4B678"/>
                    </FillStyle>
                  </fills>
                  <strokes>
                    <StrokeStyle index="1">
                      <SolidStroke scaleMode="normal">
                        <fill>
                          <SolidColor color="#654806"/>
                        </fill>
                      </SolidStroke>
                    </StrokeStyle>
                  </strokes>
                  <edges>
                    <Edge fillStyle1="1" strokeStyle="1" edges="
!416 903[425 943 457 999!457 999[492 1054 450 1088!450 1088[407 1123 382 1122!382 1122[352 1118 340 1080!340 1080[333 1039 337 987!337 987[341 933 354 896!354 896[368 860 386 860!386 860[404 864 416 903"/>
                  </edges>
                </DOMShape>
              </elements>
            </DOMFrame>
            <DOMFrame index="13" keyMode="9728">
              <elements>
                <DOMShape>
                  <fills>
                    <FillStyle index="1">
                      <SolidColor color="#F4B678"/>
                    </FillStyle>
                  </fills>
                  <strokes>
                    <StrokeStyle index="1">
                      <SolidStroke scaleMode="normal">
                        <fill>
                          <SolidColor color="#654806"/>
                        </fill>
                      </SolidStroke>
                    </StrokeStyle>
                  </strokes>
                  <edges>
                    <Edge fillStyle1="1" strokeStyle="1" edges="
!369 944[347 978 330 1041!330 1041[315 1105 262 1099!262 1099[206 1093 190 1075!190 1075[171 1051 190 1015!190 1015[214 982 253 947!253 947[294 912 329 895!329 895[365 880 377 893!377 893[388 908 369 944"/>
                  </edges>
                </DOMShape>
              </elements>
            </DOMFrame>
          </frames>
        </DOMLayer>
        <DOMLayer name="Layer 2" color="#9933CC">
          <frames>
            <DOMFrame index="0" duration="14" keyMode="9728">
              <elements>
                <DOMShape>
                  <fills>
                    <FillStyle index="1">
                      <SolidColor color="#F4B678"/>
                    </FillStyle>
                  </fills>
                  <strokes>
                    <StrokeStyle index="1">
                      <SolidStroke scaleMode="normal">
                        <fill>
                          <SolidColor color="#654806"/>
                        </fill>
                      </SolidStroke>
                    </StrokeStyle>
                  </strokes>
                  <edges>
                    <Edge fillStyle1="1" strokeStyle="1" edges="
!342 682[411 707 457 707!457 707[496 707 556 744!556 744[569 752 582 761!582 761[660 815 704 911!704 911[747 1006 626 1032!626 1032[505 1058 397 1060!397 1060[289 1061 200 1019!200 1019[111 976 192 816!192 816[214 773 235 744!235 744
[291 663 342 682"/>
                  </edges>
                </DOMShape>
              </elements>
            </DOMFrame>
          </frames>
        </DOMLayer>
        <DOMLayer name="arm" color="#9933CC" autoNamed="false">
          <frames>
            <DOMFrame index="0" duration="6" keyMode="9728">
              <elements>
                <DOMShape>
                  <fills>
                    <FillStyle index="1">
                      <SolidColor color="#F4B678"/>
                    </FillStyle>
                  </fills>
                  <strokes>
                    <StrokeStyle index="1">
                      <SolidStroke scaleMode="normal">
                        <fill>
                          <SolidColor color="#654806"/>
                        </fill>
                      </SolidStroke>
                    </StrokeStyle>
                  </strokes>
                  <edges>
                    <Edge fillStyle1="1" strokeStyle="1" edges="
!694 897[688 905 677 911!677 911[649 928 609 928!609 928[570 928 542 911!542 911[514 895 514 870!514 870[514 845 542 828!542 828[570 812 609 812!609 812[629 812 649 820!649 820[647 797 652 770!652 770[654 756 658 744!658 744[662 727 669
 713!669 713[680 690 724 683!724 683[769 676 778 733!778 733[779 739 780 744!780 744[785 793 755 817!755 817[721 845 704 878!704 878[706 863 699 850!699 850[#2B9.B3 #34F.D6 696.5 846"/>
                    <Edge fillStyle1="1" edges="
!696.5 846[703 #358.F9 703 870!703 870[703 885 694 897"/>
                    <Edge fillStyle0="1" fillStyle1="1" strokeStyle="1" edges="
!667 829[661 827 655 827!655 827[650 827 650 830!650 830[649 825 649 820!671 829[684 832 693 841!693 841[#2B5.F6 #34A.48 695 843.5!695 843.5[#2B7.B6 #34C.A 696.5 846"/>
                    <Edge fillStyle1="1" strokeStyle="1" edges="
!671 829[#29D.2 829 667 829!667 829[#29D.1 #33D.1 670 830!670 830|671 829"/>
                  </edges>
                </DOMShape>
              </elements>
            </DOMFrame>
            <DOMFrame index="6" duration="7" keyMode="9728">
              <elements>
                <DOMShape>
                  <fills>
                    <FillStyle index="1">
                      <SolidColor color="#F4B678"/>
                    </FillStyle>
                  </fills>
                  <strokes>
                    <StrokeStyle index="1">
                      <SolidStroke scaleMode="normal">
                        <fill>
                          <SolidColor color="#654806"/>
                        </fill>
                      </SolidStroke>
                    </StrokeStyle>
                  </strokes>
                  <edges>
                    <Edge fillStyle1="1" strokeStyle="1" edges="
!485 967[477 961 471 950!471 950[454 922 454 882!454 882[454 843 471 815!471 815[487 787 512 787!512 787[537 787 554 815!554 815[570 843 570 882!570 882[570 902 562 922!562 922[585 920 612 925!612 925[626 927 638 931!638 931[655 935 669
 942!669 942[692 953 699 997!699 997[706 1042 649 1051!649 1051[643 1052 638 1053!638 1053[589 1058 565 1028!565 1028[537 994 504 977!504 977[519 979 532 972"/>
                    <Edge fillStyle1="1" edges="
!532 972[#20A.AA 976 512 976!512 976[497 976 485 967"/>
                    <Edge fillStyle0="1" fillStyle1="1" strokeStyle="1" edges="
!553 940[555 934 555 928!555 928[555 923 552 923!552 923[557 922 562 922"/>
                    <Edge fillStyle1="1" strokeStyle="1" edges="
!553 944[553 #3AE.2 553 940!553 940[#228.F #3AE.1 552 943!552 943|553 944"/>
                    <Edge fillStyle0="1" fillStyle1="1" strokeStyle="1" edges="
!553 944[550 957 541 966!541 966[540 967 538 968!538 968[537 969 536 970!536 970[#216.06 #3CB.14 532 972"/>
                  </edges>
                </DOMShape>
              </elements>
            </DOMFrame>
            <DOMFrame index="13" keyMode="9728">
              <elements>
                <DOMShape>
                  <fills>
                    <FillStyle index="1">
                      <SolidColor color="#F4B678"/>
                    </FillStyle>
                  </fills>
                  <strokes>
                    <StrokeStyle index="1">
                      <SolidStroke scaleMode="normal">
                        <fill>
                          <SolidColor color="#654806"/>
                        </fill>
                      </SolidStroke>
                    </StrokeStyle>
                  </strokes>
                  <edges>
                    <Edge fillStyle1="1" strokeStyle="1" edges="
!694 897[688 905 677 911!677 911[649 928 609 928!609 928[570 928 542 911!542 911[514 895 514 870!514 870[514 845 542 828!542 828[570 812 609 812!609 812[629 812 649 820!649 820[647 797 652 770!652 770[654 756 658 744!658 744[662 727 669
 713!669 713[680 690 724 683!724 683[769 676 778 733!778 733[779 739 780 744!780 744[785 793 755 817!755 817[721 845 704 878!704 878[706 863 699 850!699 850[#2B9.B3 #34F.D6 696.5 846"/>
                    <Edge fillStyle1="1" edges="
!696.5 846[703 #358.F9 703 870!703 870[703 885 694 897"/>
                    <Edge fillStyle0="1" fillStyle1="1" strokeStyle="1" edges="
!667 829[661 827 655 827!655 827[650 827 650 830!650 830[649 825 649 820!671 829[684 832 693 841!693 841[#2B5.F6 #34A.48 695 843.5!695 843.5[#2B7.B6 #34C.A 696.5 846"/>
                    <Edge fillStyle1="1" strokeStyle="1" edges="
!670 830|671 829!671 829[#29D.2 829 667 829!667 829[#29D.1 #33D.1 670 830"/>
                  </edges>
                </DOMShape>
              </elements>
            </DOMFrame>
          </frames>
        </DOMLayer>
        <DOMLayer name="legs" color="#FF4FFF" autoNamed="false" layerType="folder"/>
        <DOMLayer name="Layer 5" color="#4FFFFF" parentLayerIndex="13" current="true" isSelected="true">
          <frames>
            <DOMFrame index="0" duration="6" keyMode="9728">
              <elements>
                <DOMShape>
                  <fills>
                    <FillStyle index="1">
                      <SolidColor color="#F4B678"/>
                    </FillStyle>
                  </fills>
                  <strokes>
                    <StrokeStyle index="1">
                      <SolidStroke scaleMode="normal">
                        <fill>
                          <SolidColor color="#654806"/>
                        </fill>
                      </SolidStroke>
                    </StrokeStyle>
                  </strokes>
                  <edges>
                    <Edge fillStyle1="1" strokeStyle="1" edges="
!433 927[478 926 524 952!524 952[570 979 591 1018!591 1018[612 1058 595 1088!595 1088[578 1117 533 1119!533 1119[488 1121 442 1094!442 1094[396 1068 375 1028!375 1028[354 988 371 959!371 959[388 929 433 927"/>
                  </edges>
                </DOMShape>
              </elements>
            </DOMFrame>
            <DOMFrame index="6" duration="7" keyMode="9728">
              <elements>
                <DOMShape>
                  <fills>
                    <FillStyle index="1">
                      <SolidColor color="#F4B678"/>
                    </FillStyle>
                  </fills>
                  <strokes>
                    <StrokeStyle index="1">
                      <SolidStroke scaleMode="normal">
                        <fill>
                          <SolidColor color="#654806"/>
                        </fill>
                      </SolidStroke>
                    </StrokeStyle>
                  </strokes>
                  <edges>
                    <Edge fillStyle1="1" strokeStyle="1" edges="
!475 939[505 956 507 1001!507 1001[508 1046 482 1092!482 1092[455 1138 416 1159!416 1159[376 1180 346 1163!346 1163[317 1146 315 1101!315 1101[313 1056 340 1010!340 1010[366 964 406 943!406 943[446 922 475 939"/>
                  </edges>
                </DOMShape>
              </elements>
            </DOMFrame>
            <DOMFrame index="13" keyMode="9728">
              <elements>
                <DOMShape>
                  <fills>
                    <FillStyle index="1">
                      <SolidColor color="#F4B678"/>
                    </FillStyle>
                  </fills>
                  <strokes>
                    <StrokeStyle index="1">
                      <SolidStroke scaleMode="normal">
                        <fill>
                          <SolidColor color="#654806"/>
                        </fill>
                      </SolidStroke>
                    </StrokeStyle>
                  </strokes>
                  <edges>
                    <Edge fillStyle1="1" strokeStyle="1" edges="
!433 927[478 926 524 952!524 952[570 979 591 1018!591 1018[612 1058 595 1088!595 1088[578 1117 533 1119!533 1119[488 1121 442 1094!442 1094[396 1068 375 1028!375 1028[354 988 371 959!371 959[388 929 433 927"/>
                  </edges>
                </DOMShape>
              </elements>
            </DOMFrame>
          </frames>
        </DOMLayer>
        <DOMLayer name="Layer 7" color="#4F80FF" parentLayerIndex="13">
          <frames>
            <DOMFrame index="0" duration="6" keyMode="9728">
              <elements>
                <DOMShape>
                  <fills>
                    <FillStyle index="1">
                      <SolidColor color="#F4B678"/>
                    </FillStyle>
                  </fills>
                  <strokes>
                    <StrokeStyle index="1">
                      <SolidStroke scaleMode="normal">
                        <fill>
                          <SolidColor color="#654806"/>
                        </fill>
                      </SolidStroke>
                    </StrokeStyle>
                  </strokes>
                  <edges>
                    <Edge fillStyle1="1" strokeStyle="1" edges="
!722 1167[676 1197 647 1221!647 1221[617 1244 592 1246!592 1246[566 1248 545 1235!545 1235[525 1222 525 1202!525 1202[525 1182 545 1168!545 1168[566 1155 592 1146!592 1146[618 1136 694 1136!694 1136[768 1136 722 1167"/>
                  </edges>
                </DOMShape>
              </elements>
            </DOMFrame>
            <DOMFrame index="6" duration="7" keyMode="9728">
              <elements>
                <DOMShape>
                  <fills>
                    <FillStyle index="1">
                      <SolidColor color="#F4B678"/>
                    </FillStyle>
                  </fills>
                  <strokes>
                    <StrokeStyle index="1">
                      <SolidStroke scaleMode="normal">
                        <fill>
                          <SolidColor color="#654806"/>
                        </fill>
                      </SolidStroke>
                    </StrokeStyle>
                  </strokes>
                  <edges>
                    <Edge fillStyle1="1" strokeStyle="1" edges="
!255 1215[221 1200 207 1180!207 1180[192 1158 192 1134!192 1134[194 1110 211 1100!211 1100[228 1090 250 1100!250 1100[273 1112 293 1130!293 1130[315 1147 353 1213!353 1213[390 1277 340 1253!340 1253[291 1228 255 1215"/>
                  </edges>
                </DOMShape>
              </elements>
            </DOMFrame>
            <DOMFrame index="13" keyMode="9728">
              <elements>
                <DOMShape>
                  <fills>
                    <FillStyle index="1">
                      <SolidColor color="#F4B678"/>
                    </FillStyle>
                  </fills>
                  <strokes>
                    <StrokeStyle index="1">
                      <SolidStroke scaleMode="normal">
                        <fill>
                          <SolidColor color="#654806"/>
                        </fill>
                      </SolidStroke>
                    </StrokeStyle>
                  </strokes>
                  <edges>
                    <Edge fillStyle1="1" strokeStyle="1" edges="
!592 1246[566 1248 545 1235!545 1235[525 1222 525 1202!525 1202[525 1182 545 1168!545 1168[566 1155 592 1146!592 1146[618 1136 694 1136!694 1136[768 1136 722 1167!722 1167[676 1197 647 1221!647 1221[617 1244 592 1246"/>
                  </edges>
                </DOMShape>
              </elements>
            </DOMFrame>
          </frames>
        </DOMLayer>
        <DOMLayer name="Layer 6" color="#808080" parentLayerIndex="13">
          <frames>
            <DOMFrame index="0" duration="6" keyMode="9728">
              <elements>
                <DOMShape>
                  <fills>
                    <FillStyle index="1">
                      <SolidColor color="#F4B678"/>
                    </FillStyle>
                  </fills>
                  <strokes>
                    <StrokeStyle index="1">
                      <SolidStroke scaleMode="normal">
                        <fill>
                          <SolidColor color="#654806"/>
                        </fill>
                      </SolidStroke>
                    </StrokeStyle>
                  </strokes>
                  <edges>
                    <Edge fillStyle1="1" strokeStyle="1" edges="
!556 1032[578 1064 590 1110!590 1110[602 1156 599 1192!599 1192[596 1229 578 1233!578 1233[561 1238 539 1208!539 1208[519 1179 507 1133!507 1133[495 1087 496 1048!496 1048[500 1012 517 1007!517 1007[535 1003 556 1032"/>
                  </edges>
                </DOMShape>
              </elements>
            </DOMFrame>
            <DOMFrame index="6" duration="7" keyMode="9728">
              <elements>
                <DOMShape>
                  <fills>
                    <FillStyle index="1">
                      <SolidColor color="#F4B678"/>
                    </FillStyle>
                  </fills>
                  <strokes>
                    <StrokeStyle index="1">
                      <SolidStroke scaleMode="normal">
                        <fill>
                          <SolidColor color="#654806"/>
                        </fill>
                      </SolidStroke>
                    </StrokeStyle>
                  </strokes>
                  <edges>
                    <Edge fillStyle1="1" strokeStyle="1" edges="
!427 1085[431 1103 402 1124!402 1124[370 1146 324 1158!324 1158[278 1170 242 1167!242 1167[205 1164 201 1146!201 1146[196 1129 226 1107!226 1107[255 1087 301 1075!301 1075[347 1063 386 1064!386 1064[422 1068 427 1085"/>
                  </edges>
                </DOMShape>
              </elements>
            </DOMFrame>
            <DOMFrame index="13" keyMode="9728">
              <elements>
                <DOMShape>
                  <fills>
                    <FillStyle index="1">
                      <SolidColor color="#F4B678"/>
                    </FillStyle>
                  </fills>
                  <strokes>
                    <StrokeStyle index="1">
                      <SolidStroke scaleMode="normal">
                        <fill>
                          <SolidColor color="#654806"/>
                        </fill>
                      </SolidStroke>
                    </StrokeStyle>
                  </strokes>
                  <edges>
                    <Edge fillStyle1="1" strokeStyle="1" edges="
!599 1192[596 1229 578 1233!578 1233[561 1238 539 1208!539 1208[519 1179 507 1133!507 1133[495 1087 496 1048!496 1048[500 1012 517 1007!517 1007[535 1003 556 1032!556 1032[578 1064 590 1110!590 1110[602 1156 599 1192"/>
                  </edges>
                </DOMShape>
              </elements>
            </DOMFrame>
          </frames>
        </DOMLayer>
        <DOMLayer name="Layer 9" color="#4FFF4F" parentLayerIndex="13">
          <frames>
            <DOMFrame index="0" duration="6" keyMode="9728">
              <elements>
                <DOMShape>
                  <fills>
                    <FillStyle index="1">
                      <SolidColor color="#F4B678"/>
                    </FillStyle>
                  </fills>
                  <strokes>
                    <StrokeStyle index="1">
                      <SolidStroke scaleMode="normal">
                        <fill>
                          <SolidColor color="#654806"/>
                        </fill>
                      </SolidStroke>
                    </StrokeStyle>
                  </strokes>
                  <edges>
                    <Edge fillStyle1="1" strokeStyle="1" edges="
!455 1189[485 1216 465 1237!465 1237[444 1257 407 1251!407 1251[369 1245 347 1235!347 1235[325 1224 292 1198!292 1198[258 1171 266 1140!266 1140[274 1109 308 1110!308 1110[342 1111 383 1137!383 1137[424 1162 455 1189"/>
                  </edges>
                </DOMShape>
              </elements>
            </DOMFrame>
            <DOMFrame index="6" duration="7" keyMode="9728">
              <elements>
                <DOMShape>
                  <fills>
                    <FillStyle index="1">
                      <SolidColor color="#F4B678"/>
                    </FillStyle>
                  </fills>
                  <strokes>
                    <StrokeStyle index="1">
                      <SolidStroke scaleMode="normal">
                        <fill>
                          <SolidColor color="#654806"/>
                        </fill>
                      </SolidStroke>
                    </StrokeStyle>
                  </strokes>
                  <edges>
                    <Edge fillStyle1="1" strokeStyle="1" edges="
!725 1083[732 1111 708 1141!708 1141[684 1170 665 1184!665 1184[644 1198 604 1213!604 1213[564 1230 541 1207!541 1207[518 1185 536 1155!536 1155[554 1127 598 1104!598 1104[639 1081 679 1068!679 1068[717 1055 725 1083"/>
                  </edges>
                </DOMShape>
              </elements>
            </DOMFrame>
            <DOMFrame index="13" keyMode="9728">
              <elements>
                <DOMShape>
                  <fills>
                    <FillStyle index="1">
                      <SolidColor color="#F4B678"/>
                    </FillStyle>
                  </fills>
                  <strokes>
                    <StrokeStyle index="1">
                      <SolidStroke scaleMode="normal">
                        <fill>
                          <SolidColor color="#654806"/>
                        </fill>
                      </SolidStroke>
                    </StrokeStyle>
                  </strokes>
                  <edges>
                    <Edge fillStyle1="1" strokeStyle="1" edges="
!407 1251[369 1245 347 1235!347 1235[325 1224 292 1198!292 1198[258 1171 266 1140!266 1140[274 1109 308 1110!308 1110[342 1111 383 1137!383 1137[424 1162 455 1189!455 1189[485 1216 465 1237!465 1237[444 1257 407 1251"/>
                  </edges>
                </DOMShape>
              </elements>
            </DOMFrame>
          </frames>
        </DOMLayer>
        <DOMLayer name="Layer 8" color="#FF4F4F" parentLayerIndex="13">
          <frames>
            <DOMFrame index="0" duration="6" keyMode="9728">
              <elements>
                <DOMShape>
                  <fills>
                    <FillStyle index="1">
                      <SolidColor color="#F4B678"/>
                    </FillStyle>
                  </fills>
                  <strokes>
                    <StrokeStyle index="1">
                      <SolidStroke scaleMode="normal">
                        <fill>
                          <SolidColor color="#654806"/>
                        </fill>
                      </SolidStroke>
                    </StrokeStyle>
                  </strokes>
                  <edges>
                    <Edge fillStyle1="1" strokeStyle="1" edges="
!386 995[412 972 424 978!424 978[437 987 429 1021!429 1021[421 1055 397 1097!397 1097[373 1138 347 1163!347 1163[320 1190 308 1181!308 1181[295 1175 303 1139!303 1139[313 1105 337 1063!337 1063[361 1022 386 995"/>
                  </edges>
                </DOMShape>
              </elements>
            </DOMFrame>
            <DOMFrame index="6" duration="7" keyMode="9728">
              <elements>
                <DOMShape>
                  <fills>
                    <FillStyle index="1">
                      <SolidColor color="#F4B678"/>
                    </FillStyle>
                  </fills>
                  <strokes>
                    <StrokeStyle index="1">
                      <SolidStroke scaleMode="normal">
                        <fill>
                          <SolidColor color="#654806"/>
                        </fill>
                      </SolidStroke>
                    </StrokeStyle>
                  </strokes>
                  <edges>
                    <Edge fillStyle1="1" strokeStyle="1" edges="
!570 1072[594 1113 602 1148!602 1148[612 1185 598 1191!598 1191[587 1200 559 1175!559 1175[535 1149 511 1107!511 1107[487 1065 476 1031!476 1031[469 996 480 989!480 989[495 983 520 1006!520 1006[546 1030 570 1072"/>
                  </edges>
                </DOMShape>
              </elements>
            </DOMFrame>
            <DOMFrame index="13" keyMode="9728">
              <elements>
                <DOMShape>
                  <fills>
                    <FillStyle index="1">
                      <SolidColor color="#F4B678"/>
                    </FillStyle>
                  </fills>
                  <strokes>
                    <StrokeStyle index="1">
                      <SolidStroke scaleMode="normal">
                        <fill>
                          <SolidColor color="#654806"/>
                        </fill>
                      </SolidStroke>
                    </StrokeStyle>
                  </strokes>
                  <edges>
                    <Edge fillStyle1="1" strokeStyle="1" edges="
!347 1163[320 1190 308 1181!308 1181[295 1175 303 1139!303 1139[313 1105 337 1063!337 1063[361 1022 386 995!386 995[412 972 424 978!424 978[437 987 429 1021!429 1021[421 1055 397 1097!397 1097[373 1138 347 1163"/>
                  </edges>
                </DOMShape>
              </elements>
            </DOMFrame>
          </frames>
        </DOMLayer>
      </layers>
    </DOMTimeline>
  </timeline>
</DOMSymbolItem>